core/__init__.py
core/ml_core.py
utils/__init__.py
utils/log.py
ml_demo-0.3.dist-info/METADATA
ml_demo-0.3.dist-info/WHEEL
ml_demo-0.3.dist-info/license.txt
ml_demo-0.3.dist-info/top_level.txt
ml_demo-0.3.dist-info/RECORD
