Metadata-Version: 2.1
Name: ml_demo
Version: 0.3
Summary: ml_demo package
Author: ming lin
Author-email: ml@ml.com
Requires-Python: >=3.6
License-File: license.txt
Requires-Dist: asyncio
